FRANECpy/__init__.py
FRANECpy/browse_and_choose_file_paths.py
FRANECpy/build_tree.py
FRANECpy/functions.py
FRANECpy/user_interface.py
FRANECpy-1.0.0.dist-info/LICENSE
FRANECpy-1.0.0.dist-info/METADATA
FRANECpy-1.0.0.dist-info/WHEEL
FRANECpy-1.0.0.dist-info/top_level.txt
FRANECpy-1.0.0.dist-info/RECORD
